MyUvStudy/Tii.py
MyUvStudy/__init__.py
MyUvStudy/bar.py
myuvstudy-0.1.6.dist-info/METADATA
myuvstudy-0.1.6.dist-info/WHEEL
myuvstudy-0.1.6.dist-info/entry_points.txt
myuvstudy-0.1.6.dist-info/RECORD
