Metadata-Version: 2.4
Name: MyUVStudy
Version: 0.1.6
Summary: Add your description here
Author-email: 解大劦 <9727005@qq.com>
Requires-Python: >=3.13
